[

    {
        "title": "档案管理",
        "href": "pages/profiles/index.html",
        "fontFamily": "ok-icon",
        "icon": "&#xe6b8;",
         "isCheck":false,
          "spread": false
    },
     {
        "title": "字段管理",
        "href": "",
        "icon": "&#xe705;",
        "spread": false,
        "children": [
            {
                "title": "客户类型",
                "href": "pages/fields/now-soft.html",
                "icon": "&#xe62e;",
                "spread": false
            },
            {
                "title": "相关业务",
                "href": "pages/fields/now-soft.html",
                "icon": "&#xe62e;",
                "spread": false
            },
            {
                "title": "现用软件品牌",
                "href": "pages/fields/now-soft.html",
                "icon": "&#xe62e;",
                "spread": false
            },
            {
                "title": "信息来源",
                "href": "pages/fields/now-soft.html",
                "icon": "&#xe62e;",
                "spread": false
            }
        ]
    },
    {
        "title": "用户管理",
        "href": "",
        "icon": "&#xe66f;",
        "spread": false,
        "children": [
            {
                "title": "用户列表",
                "href": "pages/users/user.html",
                "fontFamily": "layui-icon",
                "icon": "&#xe62e;",
                "spread": false
            },
            {
                "title": "角色列表",
                "href": "pages/users/role.html",
                "icon": "&#xe62e;",
                "spread": false
            },
            {
                "title": "权限列表",
                "href": "pages/users/permission.html",
                "icon": "&#xe62e;",
                "spread": false
            }
        ]
    },
    {
        "title": "统计分析",
        "href": "",
        "icon": "&#xe62c;",
        "spread": false,
        "children": [
            {
                "title": "各阶段客户数量",
                "fontFamily": "ok-icon",
                "icon": "&#xe882;",
                "spread": false,
                "href": "pages/statistic/chart1.html"
            },
            {
                "title": "客户构成",
                "fontFamily": "ok-icon",
                "icon": "&#xe882;",
                "spread": false,
                "href": "pages/statistic/chart2.html"
            },
            {
                "title": "新增客户数量",
                "fontFamily": "ok-icon",
                "icon": "&#xe882;",
                "spread": false,
                "href": "pages/statistic/chart3.html"
            }

        ]
    },
    {
        "title": "系统设置",
        "icon": "&#xe636;",
        "spread": false,
        "children":[
            
        ]

    },
    {
        "title": "销售人员信息管理",
        "href": "",
        "icon": "&#xe636;",
        "spread": false,
        "href": "pages/salesman/user.html"
    },
    {
        "title": "系统安全",
        "icon": "&#xe62d;",
        "spread": false,
        "children": [
            {
                "title": "数据备份与还原",
                "href": "pages/settings/data-back.html",
                "icon": "&#xe62e;",
                "spread": false
            },
            {
                "title": "安全设置",
                "href": "pages/settings/security-set.html",
                "icon": "&#xe62e;",
                "spread": false
            }
        ]
    }


]
